{"data_mtime": 1625839795, "dep_lines": [1, 2, 3, 30, 1, 1], "dep_prios": [10, 5, 5, 5, 5, 30], "dependencies": ["sys", "types", "typing", "_thread", "builtins", "abc"], "hash": "fff78b7d7cf51f2825e6cc0aa082f8259b50f890482a4afec84c4ac0a97a783d", "id": "threading", "ignore_all": true, "interface_hash": "d69493bafd6d3e245ee023f3d0c32759bc7c47c40127385bf79e2c25f4e6c072", "mtime": 1612794159, "options": {"allow_redefinition": true, "allow_untyped_globals": false, "always_false": [], "always_true": [], "bazel": false, "check_untyped_defs": true, "disallow_any_decorated": false, "disallow_any_explicit": false, "disallow_any_expr": false, "disallow_any_generics": true, "disallow_any_unimported": false, "disallow_incomplete_defs": true, "disallow_subclassing_any": true, "disallow_untyped_calls": true, "disallow_untyped_decorators": true, "disallow_untyped_defs": true, "follow_imports": "silent", "follow_imports_for_stubs": false, "ignore_errors": false, "ignore_missing_imports": true, "implicit_reexport": false, "local_partial_types": false, "mypyc": false, "no_implicit_optional": true, "platform": "darwin", "plugins": [], "show_none_errors": true, "strict_equality": true, "strict_optional": true, "strict_optional_whitelist": null, "warn_no_return": true, "warn_return_any": true, "warn_unreachable": true, "warn_unused_ignores": true}, "path": "/Library/Frameworks/Python.framework/Versions/3.9/lib/python3.9/site-packages/mypy/typeshed/stdlib/2and3/threading.pyi", "plugin_data": null, "size": 6309, "suppressed": [], "version_id": "0.800"}